Workbook

Sheet Projecaousuarios
A1: Mercado Potencial | B1: % Progressão | C1: Conversão | D1: Preço
A2: 785000 | B2: 0.0033333333 | C2: 0.1 | D2: 14.9
B3: 0.00122 | F3: Mês | G3: % Atração | H3: Usuarios | I3: Assinantes | J3: Receita
F4: 1 | G4: 0.0033 | H4: =$A$2*G4 -> 2590.5 | I4: =H4*$C$2 -> 259.05 | J4: =I4*$D$2 -> 3859.845
F5: 2 | G5: =G4+$B$2 -> 0.0066333333 | H5: =$A$2*G5 -> 5207.1667 | I5: =H5*$C$2 -> 520.71667 | J5: =I5*$D$2 -> 7758.6783
F6: 3 | G6: =G5+$B$2 -> 0.0099666667 | H6: =$A$2*G6 -> 7823.8333 | I6: =H6*$C$2 -> 782.38333 | J6: =I6*$D$2 -> 11657.512
F7: 4 | G7: =G6+$B$3 -> 0.011186667 | H7: =$A$2*G7 -> 8781.5333 | I7: =H7*$C$2 -> 878.15333 | J7: =I7*$D$2 -> 13084.485
F8: 5 | G8: =G7+$B$3 -> 0.012406667 | H8: =$A$2*G8 -> 9739.2333 | I8: =H8*$C$2 -> 973.92333 | J8: =I8*$D$2 -> 14511.458
F9: 6 | G9: =G8+$B$3 -> 0.013626667 | H9: =$A$2*G9 -> 10696.933 | I9: =H9*$C$2 -> 1069.6933 | J9: =I9*$D$2 -> 15938.431
F10: 7 | G10: =G9+$B$3 -> 0.014846667 | H10: =$A$2*G10 -> 11654.633 | I10: =H10*$C$2 -> 1165.4633 | J10: =I10*$D$2 -> 17365.404
F11: 8 | G11: =G10+$B$3 -> 0.016066667 | H11: =$A$2*G11 -> 12612.333 | I11: =H11*$C$2 -> 1261.2333 | J11: =I11*$D$2 -> 18792.377
F12: 9 | G12: =G11+$B$3 -> 0.017286667 | H12: =$A$2*G12 -> 13570.033 | I12: =H12*$C$2 -> 1357.0033 | J12: =I12*$D$2 -> 20219.35
F13: 10 | G13: =G12+$B$3 -> 0.018506667 | H13: =$A$2*G13 -> 14527.733 | I13: =H13*$C$2 -> 1452.7733 | J13: =I13*$D$2 -> 21646.323
F14: 11 | G14: =G13+$B$3 -> 0.019726667 | H14: =$A$2*G14 -> 15485.433 | I14: =H14*$C$2 -> 1548.5433 | J14: =I14*$D$2 -> 23073.296
F15: 12 | G15: =G14+$B$3 -> 0.020946667 | H15: =$A$2*G15 -> 16443.133 | I15: =H15*$C$2 -> 1644.3133 | J15: =I15*$D$2 -> 24500.269

Sheet Analiseinvestimento
A1: TMA (a.m) | B1: 0.008
A2: TMA (a.a) | B2: =B1*12 -> 0.096
J4: Indicadores de Viabilidade Econômica (TMA 0,8% mês ou 9,6% ano)
B5: Mês | C5: Despesa | D5: Receita | E5: Fluxo de caixa | F5: FC a valor presente | G5: Valor a recuperar | J5: Ponto de Equilíbrio: | L5: terceiro mês
B6: 0 | C6: 14000 | D6: 0 | G6: -14000 | J6: Payback descontado: | L6: oitavo mês
B7: 1 | C7: 10150 | D7: =Projecaousuarios!J4 -> 3859.845 | E7: =D7-C7 -> -6290.155 | F7: =PV($B$1,B7,,-E7) -> -6240.2331 | G7: =F7+G6 -> -20240.233 | J7: Valor Presente Líquido: | L7: R$ 46.257,46
B8: 2 | C8: 10150 | D8: =Projecaousuarios!J5 -> 7758.6783 | E8: =D8-C8 -> -2391.3217 | F8: =PV($B$1,B8,,-E8) -> -2353.5148 | G8: =G7+F8 -> -22593.748 | J8: Taxa Interna de Retorno: | L8: 0.38
A9: P.Equilibrio | B9: 3 | C9: 10150 | D9: =Projecaousuarios!J6 -> 11657.512 | E9: =D9-C9 -> 1507.5117 | F9: =PV($B$1,B9,,-E9) -> 1471.9026 | G9: =G8+F9 -> -21121.845
B10: 4 | C10: 10150 | D10: =Projecaousuarios!J7 -> 13084.485 | E10: =D10-C10 -> 2934.4847 | F10: =PV($B$1,B10,,-E10) -> 2842.4296 | G10: =G9+F10 -> -18279.416
B11: 5 | C11: 10150 | D11: =Projecaousuarios!J8 -> 14511.458 | E11: =D11-C11 -> 4361.4577 | F11: =PV($B$1,B11,,-E11) -> 4191.1094 | G11: =G10+F11 -> -14088.306
B12: 6 | C12: 10150 | D12: =Projecaousuarios!J9 -> 15938.431 | E12: =D12-C12 -> 5788.4307 | F12: =PV($B$1,B12,,-E12) -> 5518.2026 | G12: =G11+F12 -> -8570.1037
B13: 7 | C13: 10150 | D13: =Projecaousuarios!J10 -> 17365.404 | E13: =D13-C13 -> 7215.4037 | F13: =PV($B$1,B13,,-E13) -> 6823.9668 | G13: =G12+F13 -> -1746.1368
A14: PAYBACK | B14: 8 | C14: 10150 | D14: =Projecaousuarios!J11 -> 18792.377 | E14: =D14-C14 -> 8642.3767 | F14: =PV($B$1,B14,,-E14) -> 8108.6571
B15: 9 | C15: 10150 | D15: =Projecaousuarios!J12 -> 20219.35 | E15: =D15-C15 -> 10069.35 | F15: =PV($B$1,B15,,-E15) -> 9372.5256
B16: 10 | C16: 10150 | D16: =Projecaousuarios!J13 -> 21646.323 | E16: =D16-C16 -> 11496.323 | F16: =PV($B$1,B16,,-E16) -> 10615.822
B17: 11 | C17: 10150 | D17: =Projecaousuarios!J14 -> 23073.296 | E17: =D17-C17 -> 12923.296 | F17: =PV($B$1,B17,,-E17) -> 11838.793
B18: 12 | C18: 10150 | D18: =Projecaousuarios!J15 -> 24500.269 | E18: =D18-C18 -> 14350.269 | F18: =PV($B$1,B18,,-E18) -> 13041.683
A21: VPL | B21: {=NPV(B1,F7:F18)-C6} -> 46257.46
A22: TIR | B22: =IRR(F7:F18) -> 0.38476456
